gh_pydantic_ai/__init__.py
gh_pydantic_ai/__main__.py
gh_pydantic_ai/agent.py
gh_pydantic_ai/agent_cli.py
gh_pydantic_ai/auth.py
gh_pydantic_ai/cli.py
gh_pydantic_ai/client.py
gh_pydantic_ai/consts.py
gh_pydantic_ai/headers.py
gh_pydantic_ai/model.py
gh_pydantic_ai/provider.py
gh_pydantic_ai/py.typed
gh_pydantic_ai/types.py
gh_pydantic_ai-0.3.0.dist-info/METADATA
gh_pydantic_ai-0.3.0.dist-info/WHEEL
gh_pydantic_ai-0.3.0.dist-info/entry_points.txt
gh_pydantic_ai-0.3.0.dist-info/licenses/LICENSE
gh_pydantic_ai-0.3.0.dist-info/RECORD
